Workbook

Sheet INSTRUCCIONES
A1: CONTABILIDAD 3T 2026 — RP CHARGER SL y PROIM BALEAR SL
A2: Julio, agosto y septiembre de 2026. Primer trimestre construido con este modelo.
B5: QUÉ ES ESTO
C6: El cuaderno donde se hace la contabilidad del trimestre. Entran facturas, movimientos de banco
C7: y nóminas; sale el asiento en formato de importación a ContaSOL y la liquidación de IVA.
C8: No sustituye a ContaSOL: prepara lo que se importa en él.
B10: EL MÉTODO, EN CINCO PASOS
B11: 1. Facturas | C11: Se vuelcan las emitidas y las recibidas del trimestre con su base, tipo y cuota.
B12: 2. Banco | C12: Cada movimiento con su contrapartida. Lo que no se sepa va a la cuenta de dudas.
B13: 3. Nóminas | C13: El asiento mensual que ya produce /generar-apu-nominas.
B14: 4. Asientos | C14: Se consolida todo y se comprueba que DEBE = HABER.
B15: 5. IVA | C15: La liquidación sale de las facturas, no de los asientos: así son dos cálculos
C16: independientes que tienen que dar lo mismo. Si no coinciden, hay un error.
B18: REGLA DE ORO
C19: No se inventa un apunte para poder continuar. Lo que no esté claro va a la cuenta de dudas
C20: (555000000 en RP, 555000002 en PROIM) y se pregunta. Es la misma regla que ya gobierna
C21: las conciliaciones, y aquí importa más, porque esto acaba en los libros oficiales.
B23: COLORES
B24: Azul | C24: Se teclea. Es un dato que viene de un documento real.
B25: Negro | C25: Fórmula. No se toca.
B26: Verde | C26: Viene de otra hoja de este mismo cuaderno.
B27: Fondo amarillo | C27: Pendiente de rellenar.
B29: ANTES DE IMPORTAR A CONTASOL
C30: Mirar la hoja CONTROL. Si algún cuadre sale en rojo, no se importa: se corrige primero.
B32: AVISO
C33: Los tipos, umbrales y plazos hay que verificarlos contra la normativa vigente en AEAT.
C34: Este cuaderno prepara el trabajo; la declaración la revisa y firma el asesor fiscal.

Sheet PLAN
A1: Plan del 3T 2026
A2: Hoy: 19/09/2026. La ruta crítica es reclamar las facturas que faltan: es lo único que depende de terceros.
A4: # | B4: BLOQUE | C4: TAREA | D4: EMPRESA | E4: DESDE | F4: HASTA | G4: DÍAS | H4: RESPONSABLE | I4: ESTADO | J4: NOTA
A5: 1 | B5: RUTA CRÍTICA | C5: Sacar la lista de facturas de proveedor que faltan (julio y agosto) | D5: Las dos | E5: 46284 | F5: 46287 | G5: =F5-E5 | H5: Contable | I5: PENDIENTE | J5: De la hoja FALTAN de PENDIENTES_*.xlsx
A6: 2 | B6: RUTA CRÍTICA | C6: Reclamar esas facturas a cada proveedor | D6: Las dos | E6: 46287 | F6: 46291 | G6: =F6-E6 | H6: Administración | I6: PENDIENTE | J6: Un proveedor tarda 1-2 semanas. Por eso va primero
A7: 3 | B7: Documentación | C7: Cerrar julio y agosto: extractos y justificantes completos | D7: Las dos | E7: 46284 | F7: 46291 | G7: =F7-E7 | H7: Contable | I7: PENDIENTE | J7: /descargar-bancos + /clasificar-comunicados-bancos
A8: 4 | B8: Documentación | C8: Septiembre parcial 01-15: extracto y papeles | D8: Las dos | E8: 46287 | F8: 46291 | G8: =F8-E8 | H8: Contable | I8: PENDIENTE | J8: Adelanta trabajo; el mes entero se baja después
A9: 5 | B9: Contabilización | C9: Volcar facturas emitidas y recibidas de julio y agosto | D9: Las dos | E9: 46291 | F9: 46298 | G9: =F9-E9 | H9: Contable | I9: PENDIENTE | J9: Hojas F_EMITIDAS y F_RECIBIDAS
A10: 6 | B10: Contabilización | C10: TPV: comprobar que se contabiliza el bruto y la comisión aparte | D10: RP CHARGER | E10: 46291 | F10: 46298 | G10: =F10-E10 | H10: Contable | I10: PENDIENTE | J10: /depurar-extracto-tpv da la columna COMISION OPERACION
A11: 7 | B11: Documentación | C11: Septiembre entero: extracto y papeles del 16 al 30 | D11: Las dos | E11: 46296 | F11: 46300 | G11: =F11-E11 | H11: Contable | I11: PENDIENTE | J11: Se borra el parcial cuando el entero lo cubra
A12: 8 | B12: Contabilización | C12: Nóminas de julio, agosto y septiembre | D12: Las dos | E12: 46296 | F12: 46301 | G12: =F12-E12 | H12: Contable | I12: PENDIENTE | J12: /generar-apu-nominas. En RP se suman 00094+00095+00096
A13: 9 | B13: Contabilización | C13: Volcar facturas de septiembre | D13: Las dos | E13: 46300 | F13: 46303 | G13: =F13-E13 | H13: Contable | I13: PENDIENTE
A14: 10 | B14: Conciliación | C14: Contrapartidas de los tres meses | D14: Las dos | E14: 46301 | F14: 46305 | G14: =F14-E14 | H14: Contable | I14: PENDIENTE | J14: /conciliar-caixa-rpcharger y /conciliar-banco-proim
A15: 11 | B15: Conciliación | C15: Resolver las dudas de la 555 y dejarla a cero | D15: Las dos | E15: 46303 | F15: 46307 | G15: =F15-E15 | H15: Dirección | I15: PENDIENTE | J15: Cada euro en la 555 es contabilidad sin terminar
A16: 12 | B16: Control | C16: Cuadrar banco contra contabilidad, cuenta por cuenta | D16: Las dos | E16: 46305 | F16: 46307 | G16: =F16-E16 | H16: Contable | I16: PENDIENTE | J16: Hoja CONTROL
A17: 13 | B17: Control | C17: Revisión fiscal del trimestre | D17: Las dos | E17: 46307 | F17: 46309 | G17: =F17-E17 | H17: Contable | I17: PENDIENTE | J17: /revisar-contabilidad
A18: 14 | B18: Declaración | C18: Liquidación del IVA y cuadre del 303 | D18: Las dos | E18: 46308 | F18: 46309 | G18: =F18-E18 | H18: Contable | I18: PENDIENTE | J18: Hoja IVA_303
A19: 15 | B19: Declaración | C19: Retenciones: 111 y 115 | D19: Las dos | E19: 46308 | F19: 46309 | G19: =F19-E19 | H19: Contable | I19: PENDIENTE | J19: Hoja RETENCIONES
A20: 16 | B20: Declaración | C20: Revisión del asesor antes de presentar | D20: Las dos | E20: 46309 | F20: 46310 | G20: =F20-E20 | H20: Asesor | I20: PENDIENTE | J20: Última parada antes de firmar
A21: 17 | B21: Declaración | C21: Presentar — SI SE DOMICILIA EL PAGO, EL PLAZO ES EL 15 | D21: Las dos | E21: 46310 | F21: 46315 | G21: =F21-E21 | H21: Asesor | I21: PENDIENTE | J21: Verificar plazos en el calendario AEAT del ejercicio
B23: Avance del trimestre | C23: =IFERROR(COUNTIF(I5:I21,"HECHO")/COUNTA(I5:I21),0)

Sheet F_EMITIDAS
A1: Facturas emitidas — 3T 2026
A2: Una fila por factura. La numeración tiene que ser correlativa y sin huecos: un hueco hay que poder explicarlo.
A4: EMPRESA | B4: MES | C4: FECHA | D4: Nº FACTURA | E4: CLIENTE | F4: NIF | G4: CUENTA CLIENTE | H4: BASE | I4: TIPO | J4: CUOTA IVA | K4: TOTAL | L4: CUENTA INGRESO | M4: ISP | N4: OBSERVACIONES
A5: EJEMPLO | B5: 07 | C5: 46217 | D5: 2026/0118 | E5: Fila de ejemplo: EMPRESA=EJEMPLO no suma en IVA_303. Bórrala o sobrescríbela. | F5: B07xxxxxx | G5: 430000143 | H5: 2400 | I5: 0.21 | J5: =IF(N(H5)=0,"",IF(M5="SI",0,ROUND(H5*I5,2))) | K5: =IF(N(H5)=0,"",H5+N(J5)) | L5: 700000001 | M5: NO
J6: =IF(N(H6)=0,"",IF(M6="SI",0,ROUND(H6*I6,2))) | K6: =IF(N(H6)=0,"",H6+N(J6))
J7: =IF(N(H7)=0,"",IF(M7="SI",0,ROUND(H7*I7,2))) | K7: =IF(N(H7)=0,"",H7+N(J7))
J8: =IF(N(H8)=0,"",IF(M8="SI",0,ROUND(H8*I8,2))) | K8: =IF(N(H8)=0,"",H8+N(J8))
J9: =IF(N(H9)=0,"",IF(M9="SI",0,ROUND(H9*I9,2))) | K9: =IF(N(H9)=0,"",H9+N(J9))
J10: =IF(N(H10)=0,"",IF(M10="SI",0,ROUND(H10*I10,2))) | K10: =IF(N(H10)=0,"",H10+N(J10))
J11: =IF(N(H11)=0,"",IF(M11="SI",0,ROUND(H11*I11,2))) | K11: =IF(N(H11)=0,"",H11+N(J11))
J12: =IF(N(H12)=0,"",IF(M12="SI",0,ROUND(H12*I12,2))) | K12: =IF(N(H12)=0,"",H12+N(J12))
J13: =IF(N(H13)=0,"",IF(M13="SI",0,ROUND(H13*I13,2))) | K13: =IF(N(H13)=0,"",H13+N(J13))
J14: =IF(N(H14)=0,"",IF(M14="SI",0,ROUND(H14*I14,2))) | K14: =IF(N(H14)=0,"",H14+N(J14))
J15: =IF(N(H15)=0,"",IF(M15="SI",0,ROUND(H15*I15,2))) | K15: =IF(N(H15)=0,"",H15+N(J15))
J16: =IF(N(H16)=0,"",IF(M16="SI",0,ROUND(H16*I16,2))) | K16: =IF(N(H16)=0,"",H16+N(J16))
J17: =IF(N(H17)=0,"",IF(M17="SI",0,ROUND(H17*I17,2))) | K17: =IF(N(H17)=0,"",H17+N(J17))
... J404: =IF(N(H404)=0,"",IF(M404="SI",0,ROUND(H404*I404,2))) | K404: =IF(N(H404)=0,"",H404+N(J404))

Sheet F_RECIBIDAS
A1: Facturas recibidas — 3T 2026
A2: El IVA se deduce en el periodo en que se recibe y registra la factura: por eso hay dos fechas.
A4: EMPRESA | B4: MES | C4: FECHA FRA | D4: FECHA RECEP. | E4: Nº FACTURA | F4: PROVEEDOR | G4: NIF | H4: CUENTA PROV. | I4: BASE | J4: TIPO | K4: CUOTA IVA | L4: TOTAL | M4: CUENTA GASTO | N4: % DEDUC. | O4: IVA DEDUCIBLE | P4: ISP | Q4: B. INVERSIÓN | R4: OBSERVACIONES
A5: EJEMPLO | B5: 07 | C5: 46206 | D5: 46212 | E5: A-2026-551 | F5: Fila de ejemplo: EMPRESA=EJEMPLO no suma en IVA_303. Bórrala o sobrescríbela. | G5: B07xxxxxx | H5: 400000183 | I5: 1850 | J5: 0.21 | K5: =IF(N(I5)=0,"",ROUND(I5*J5,2)) | L5: =IF(N(I5)=0,"",IF(P5="SI",I5,I5+N(K5))) | M5: 600000001 | N5: 1 | O5: =IF(N(I5)=0,"",ROUND(N(K5)*N(N5),2)) | P5: NO | Q5: NO
K6: =IF(N(I6)=0,"",ROUND(I6*J6,2)) | L6: =IF(N(I6)=0,"",IF(P6="SI",I6,I6+N(K6))) | O6: =IF(N(I6)=0,"",ROUND(N(K6)*N(N6),2))
K7: =IF(N(I7)=0,"",ROUND(I7*J7,2)) | L7: =IF(N(I7)=0,"",IF(P7="SI",I7,I7+N(K7))) | O7: =IF(N(I7)=0,"",ROUND(N(K7)*N(N7),2))
K8: =IF(N(I8)=0,"",ROUND(I8*J8,2)) | L8: =IF(N(I8)=0,"",IF(P8="SI",I8,I8+N(K8))) | O8: =IF(N(I8)=0,"",ROUND(N(K8)*N(N8),2))
K9: =IF(N(I9)=0,"",ROUND(I9*J9,2)) | L9: =IF(N(I9)=0,"",IF(P9="SI",I9,I9+N(K9))) | O9: =IF(N(I9)=0,"",ROUND(N(K9)*N(N9),2))
K10: =IF(N(I10)=0,"",ROUND(I10*J10,2)) | L10: =IF(N(I10)=0,"",IF(P10="SI",I10,I10+N(K10))) | O10: =IF(N(I10)=0,"",ROUND(N(K10)*N(N10),2))
K11: =IF(N(I11)=0,"",ROUND(I11*J11,2)) | L11: =IF(N(I11)=0,"",IF(P11="SI",I11,I11+N(K11))) | O11: =IF(N(I11)=0,"",ROUND(N(K11)*N(N11),2))
K12: =IF(N(I12)=0,"",ROUND(I12*J12,2)) | L12: =IF(N(I12)=0,"",IF(P12="SI",I12,I12+N(K12))) | O12: =IF(N(I12)=0,"",ROUND(N(K12)*N(N12),2))
K13: =IF(N(I13)=0,"",ROUND(I13*J13,2)) | L13: =IF(N(I13)=0,"",IF(P13="SI",I13,I13+N(K13))) | O13: =IF(N(I13)=0,"",ROUND(N(K13)*N(N13),2))
K14: =IF(N(I14)=0,"",ROUND(I14*J14,2)) | L14: =IF(N(I14)=0,"",IF(P14="SI",I14,I14+N(K14))) | O14: =IF(N(I14)=0,"",ROUND(N(K14)*N(N14),2))
K15: =IF(N(I15)=0,"",ROUND(I15*J15,2)) | L15: =IF(N(I15)=0,"",IF(P15="SI",I15,I15+N(K15))) | O15: =IF(N(I15)=0,"",ROUND(N(K15)*N(N15),2))
K16: =IF(N(I16)=0,"",ROUND(I16*J16,2)) | L16: =IF(N(I16)=0,"",IF(P16="SI",I16,I16+N(K16))) | O16: =IF(N(I16)=0,"",ROUND(N(K16)*N(N16),2))
K17: =IF(N(I17)=0,"",ROUND(I17*J17,2)) | L17: =IF(N(I17)=0,"",IF(P17="SI",I17,I17+N(K17))) | O17: =IF(N(I17)=0,"",ROUND(N(K17)*N(N17),2))
... K404: =IF(N(I404)=0,"",ROUND(I404*J404,2)) | L404: =IF(N(I404)=0,"",IF(P404="SI",I404,I404+N(K404))) | O404: =IF(N(I404)=0,"",ROUND(N(K404)*N(N404),2))
F406: % DEDUC.: 1 = 100%. Vehículos de turismo, 0,5 salvo prueba de afectación exclusiva. Atenciones a clientes y regalos, 0.

Sheet BANCO
A1: Movimientos de banco — 3T 2026
A2: Sale de los extractos definitivos. La contrapartida la rellena /conciliar-*; lo que no se sepa, a la cuenta de dudas.
A4: EMPRESA | B4: CUENTA 572 | C4: MES | D4: FECHA | E4: CATEGORÍA | F4: DESCRIPCIÓN | G4: IMPORTE | H4: SALDO | I4: CONTRAPARTIDA | J4: MOTIVO | K4: COLOR | L4: PAPEL

Sheet NOMINAS
A1: Nóminas — 3T 2026
A2: Los totales del asiento que produce /generar-apu-nominas. En RP CHARGER se suman las tres sub-empresas (00094, 00095, 00096).
A4: EMPRESA | B4: MES | C4: 640 Sueldos | D4: 642 SS empresa | E4: 476 Organismos SS | F4: 4751 IRPF | G4: 465 Líquido | H4: 460 Anticipos | I4: 478 Embargos | J4: DEBE | K4: HABER | L4: CUADRE
A5: RP | B5: 07 | J5: =N(C5)+N(D5) | K5: =N(E5)+N(F5)+N(G5)+N(H5)+N(I5) | L5: =IF(ROUND(J5-K5,2)=0,"OK","DESCUADRA "&TEXT(J5-K5,"0.00"))
A6: RP | B6: 08 | J6: =N(C6)+N(D6) | K6: =N(E6)+N(F6)+N(G6)+N(H6)+N(I6) | L6: =IF(ROUND(J6-K6,2)=0,"OK","DESCUADRA "&TEXT(J6-K6,"0.00"))
A7: RP | B7: 09 | J7: =N(C7)+N(D7) | K7: =N(E7)+N(F7)+N(G7)+N(H7)+N(I7) | L7: =IF(ROUND(J7-K7,2)=0,"OK","DESCUADRA "&TEXT(J7-K7,"0.00"))
A8: PROIM | B8: 07 | J8: =N(C8)+N(D8) | K8: =N(E8)+N(F8)+N(G8)+N(H8)+N(I8) | L8: =IF(ROUND(J8-K8,2)=0,"OK","DESCUADRA "&TEXT(J8-K8,"0.00"))
A9: PROIM | B9: 08 | J9: =N(C9)+N(D9) | K9: =N(E9)+N(F9)+N(G9)+N(H9)+N(I9) | L9: =IF(ROUND(J9-K9,2)=0,"OK","DESCUADRA "&TEXT(J9-K9,"0.00"))
A10: PROIM | B10: 09 | J10: =N(C10)+N(D10) | K10: =N(E10)+N(F10)+N(G10)+N(H10)+N(I10) | L10: =IF(ROUND(J10-K10,2)=0,"OK","DESCUADRA "&TEXT(J10-K10,"0.00"))
B12: Regla dura: 640 + 642 = 476 + 4751 + 465 + 460 + 478. Si un mes no cuadra al céntimo, no se genera el asiento: se revisa.

Sheet IVA_303
A1: Liquidación de IVA — 3T 2026
A2: Se calcula desde las facturas, no desde los asientos. Son dos caminos independientes que tienen que dar lo mismo.
B4: RP CHARGER SL
B5: CONCEPTO | C5: CASILLA | D5: JULIO | E5: AGOSTO | F5: SEPTIEMBRE | G5: TRIMESTRE
B6: IVA DEVENGADO
B7: Régimen general — base al 21% | D7: =SUMIFS('F_EMITIDAS'!$H$5:$H$404,'F_EMITIDAS'!$A$5:$A$404,"RP",'F_EMITIDAS'!$B$5:$B$404,"07",'F_EMITIDAS'!$M$5:$M$404,"NO",'F_EMITIDAS'!$I$5:$I$404,0.21) | E7: =SUMIFS('F_EMITIDAS'!$H$5:$H$404,'F_EMITIDAS'!$A$5:$A$404,"RP",'F_EMITIDAS'!$B$5:$B$404,"08",'F_EMITIDAS'!$M$5:$M$404,"NO",'F_EMITIDAS'!$I$5:$I$404,0.21) | F7: =SUMIFS('F_EMITIDAS'!$H$5:$H$404,'F_EMITIDAS'!$A$5:$A$404,"RP",'F_EMITIDAS'!$B$5:$B$404,"09",'F_EMITIDAS'!$M$5:$M$404,"NO",'F_EMITIDAS'!$I$5:$I$404,0.21) | G7: =SUM(D7:F7)
B8: Régimen general — base al 10% | D8: =SUMIFS('F_EMITIDAS'!$H$5:$H$404,'F_EMITIDAS'!$A$5:$A$404,"RP",'F_EMITIDAS'!$B$5:$B$404,"07",'F_EMITIDAS'!$M$5:$M$404,"NO",'F_EMITIDAS'!$I$5:$I$404,0.1) | E8: =SUMIFS('F_EMITIDAS'!$H$5:$H$404,'F_EMITIDAS'!$A$5:$A$404,"RP",'F_EMITIDAS'!$B$5:$B$404,"08",'F_EMITIDAS'!$M$5:$M$404,"NO",'F_EMITIDAS'!$I$5:$I$404,0.1) | F8: =SUMIFS('F_EMITIDAS'!$H$5:$H$404,'F_EMITIDAS'!$A$5:$A$404,"RP",'F_EMITIDAS'!$B$5:$B$404,"09",'F_EMITIDAS'!$M$5:$M$404,"NO",'F_EMITIDAS'!$I$5:$I$404,0.1) | G8: =SUM(D8:F8)
B9: Régimen general — base al 4% | D9: =SUMIFS('F_EMITIDAS'!$H$5:$H$404,'F_EMITIDAS'!$A$5:$A$404,"RP",'F_EMITIDAS'!$B$5:$B$404,"07",'F_EMITIDAS'!$M$5:$M$404,"NO",'F_EMITIDAS'!$I$5:$I$404,0.04) | E9: =SUMIFS('F_EMITIDAS'!$H$5:$H$404,'F_EMITIDAS'!$A$5:$A$404,"RP",'F_EMITIDAS'!$B$5:$B$404,"08",'F_EMITIDAS'!$M$5:$M$404,"NO",'F_EMITIDAS'!$I$5:$I$404,0.04) | F9: =SUMIFS('F_EMITIDAS'!$H$5:$H$404,'F_EMITIDAS'!$A$5:$A$404,"RP",'F_EMITIDAS'!$B$5:$B$404,"09",'F_EMITIDAS'!$M$5:$M$404,"NO",'F_EMITIDAS'!$I$5:$I$404,0.04) | G9: =SUM(D9:F9)
B10: Cuota devengada | D10: =SUMIFS('F_EMITIDAS'!$J$5:$J$404,'F_EMITIDAS'!$A$5:$A$404,"RP",'F_EMITIDAS'!$B$5:$B$404,"07",'F_EMITIDAS'!$M$5:$M$404,"NO") | E10: =SUMIFS('F_EMITIDAS'!$J$5:$J$404,'F_EMITIDAS'!$A$5:$A$404,"RP",'F_EMITIDAS'!$B$5:$B$404,"08",'F_EMITIDAS'!$M$5:$M$404,"NO") | F10: =SUMIFS('F_EMITIDAS'!$J$5:$J$404,'F_EMITIDAS'!$A$5:$A$404,"RP",'F_EMITIDAS'!$B$5:$B$404,"09",'F_EMITIDAS'!$M$5:$M$404,"NO") | G10: =SUM(D10:F10)
B11: ISP — base de facturas emitidas con inversión del sujeto pasivo (informativa, no suma cuota) | G11: =SUM(D11:F11)
B12: Adquisiciones intracomunitarias — cuota autorrepercutida | G12: =SUM(D12:F12)
B13: TOTAL DEVENGADO | D13: =D10+N(D12) | E13: =E10+N(E12) | F13: =F10+N(F12) | G13: =SUM(D13:F13)
B15: IVA DEDUCIBLE
B16: Operaciones interiores corrientes — base | D16: =SUMIFS('F_RECIBIDAS'!$I$5:$I$404,'F_RECIBIDAS'!$A$5:$A$404,"RP",'F_RECIBIDAS'!$B$5:$B$404,"07") | E16: =SUMIFS('F_RECIBIDAS'!$I$5:$I$404,'F_RECIBIDAS'!$A$5:$A$404,"RP",'F_RECIBIDAS'!$B$5:$B$404,"08") | F16: =SUMIFS('F_RECIBIDAS'!$I$5:$I$404,'F_RECIBIDAS'!$A$5:$A$404,"RP",'F_RECIBIDAS'!$B$5:$B$404,"09") | G16: =SUM(D16:F16)
B17: Operaciones interiores corrientes — cuota deducible | D17: =SUMIFS('F_RECIBIDAS'!$O$5:$O$404,'F_RECIBIDAS'!$A$5:$A$404,"RP",'F_RECIBIDAS'!$B$5:$B$404,"07") | E17: =SUMIFS('F_RECIBIDAS'!$O$5:$O$404,'F_RECIBIDAS'!$A$5:$A$404,"RP",'F_RECIBIDAS'!$B$5:$B$404,"08") | F17: =SUMIFS('F_RECIBIDAS'!$O$5:$O$404,'F_RECIBIDAS'!$A$5:$A$404,"RP",'F_RECIBIDAS'!$B$5:$B$404,"09") | G17: =SUM(D17:F17)
B18: Bienes de inversión — cuota deducible | G18: =SUM(D18:F18)
B19: ISP soportado — cuota deducible | G19: =SUM(D19:F19)
B20: Cuotas a compensar del periodo anterior | G20: =SUM(D20:F20)
B21: TOTAL DEDUCIBLE | D21: =D17+N(D18)+N(D19)+N(D20) | E21: =E17+N(E18)+N(E19)+N(E20) | F21: =F17+N(F18)+N(F19)+N(F20) | G21: =SUM(D21:F21)
B23: RESULTADO DEL PERIODO | D23: =D13-D21 | E23: =E13-E21 | F23: =F13-F21 | G23: =SUM(D23:F23)
B26: PROIM BALEAR SL
B27: CONCEPTO | C27: CASILLA | D27: JULIO | E27: AGOSTO | F27: SEPTIEMBRE | G27: TRIMESTRE
B28: IVA DEVENGADO
B29: Régimen general — base al 21% | D29: =SUMIFS('F_EMITIDAS'!$H$5:$H$404,'F_EMITIDAS'!$A$5:$A$404,"PROIM",'F_EMITIDAS'!$B$5:$B$404,"07",'F_EMITIDAS'!$M$5:$M$404,"NO",'F_EMITIDAS'!$I$5:$I$404,0.21) | E29: =SUMIFS('F_EMITIDAS'!$H$5:$H$404,'F_EMITIDAS'!$A$5:$A$404,"PROIM",'F_EMITIDAS'!$B$5:$B$404,"08",'F_EMITIDAS'!$M$5:$M$404,"NO",'F_EMITIDAS'!$I$5:$I$404,0.21) | F29: =SUMIFS('F_EMITIDAS'!$H$5:$H$404,'F_EMITIDAS'!$A$5:$A$404,"PROIM",'F_EMITIDAS'!$B$5:$B$404,"09",'F_EMITIDAS'!$M$5:$M$404,"NO",'F_EMITIDAS'!$I$5:$I$404,0.21) | G29: =SUM(D29:F29)
B30: Régimen general — base al 10% | D30: =SUMIFS('F_EMITIDAS'!$H$5:$H$404,'F_EMITIDAS'!$A$5:$A$404,"PROIM",'F_EMITIDAS'!$B$5:$B$404,"07",'F_EMITIDAS'!$M$5:$M$404,"NO",'F_EMITIDAS'!$I$5:$I$404,0.1) | E30: =SUMIFS('F_EMITIDAS'!$H$5:$H$404,'F_EMITIDAS'!$A$5:$A$404,"PROIM",'F_EMITIDAS'!$B$5:$B$404,"08",'F_EMITIDAS'!$M$5:$M$404,"NO",'F_EMITIDAS'!$I$5:$I$404,0.1) | F30: =SUMIFS('F_EMITIDAS'!$H$5:$H$404,'F_EMITIDAS'!$A$5:$A$404,"PROIM",'F_EMITIDAS'!$B$5:$B$404,"09",'F_EMITIDAS'!$M$5:$M$404,"NO",'F_EMITIDAS'!$I$5:$I$404,0.1) | G30: =SUM(D30:F30)
B31: Régimen general — base al 4% | D31: =SUMIFS('F_EMITIDAS'!$H$5:$H$404,'F_EMITIDAS'!$A$5:$A$404,"PROIM",'F_EMITIDAS'!$B$5:$B$404,"07",'F_EMITIDAS'!$M$5:$M$404,"NO",'F_EMITIDAS'!$I$5:$I$404,0.04) | E31: =SUMIFS('F_EMITIDAS'!$H$5:$H$404,'F_EMITIDAS'!$A$5:$A$404,"PROIM",'F_EMITIDAS'!$B$5:$B$404,"08",'F_EMITIDAS'!$M$5:$M$404,"NO",'F_EMITIDAS'!$I$5:$I$404,0.04) | F31: =SUMIFS('F_EMITIDAS'!$H$5:$H$404,'F_EMITIDAS'!$A$5:$A$404,"PROIM",'F_EMITIDAS'!$B$5:$B$404,"09",'F_EMITIDAS'!$M$5:$M$404,"NO",'F_EMITIDAS'!$I$5:$I$404,0.04) | G31: =SUM(D31:F31)
B32: Cuota devengada | D32: =SUMIFS('F_EMITIDAS'!$J$5:$J$404,'F_EMITIDAS'!$A$5:$A$404,"PROIM",'F_EMITIDAS'!$B$5:$B$404,"07",'F_EMITIDAS'!$M$5:$M$404,"NO") | E32: =SUMIFS('F_EMITIDAS'!$J$5:$J$404,'F_EMITIDAS'!$A$5:$A$404,"PROIM",'F_EMITIDAS'!$B$5:$B$404,"08",'F_EMITIDAS'!$M$5:$M$404,"NO") | F32: =SUMIFS('F_EMITIDAS'!$J$5:$J$404,'F_EMITIDAS'!$A$5:$A$404,"PROIM",'F_EMITIDAS'!$B$5:$B$404,"09",'F_EMITIDAS'!$M$5:$M$404,"NO") | G32: =SUM(D32:F32)
B33: ISP — base de facturas emitidas con inversión del sujeto pasivo (informativa, no suma cuota) | G33: =SUM(D33:F33)
B34: Adquisiciones intracomunitarias — cuota autorrepercutida | G34: =SUM(D34:F34)
B35: TOTAL DEVENGADO | D35: =D32+N(D34) | E35: =E32+N(E34) | F35: =F32+N(F34) | G35: =SUM(D35:F35)
B37: IVA DEDUCIBLE
B38: Operaciones interiores corrientes — base | D38: =SUMIFS('F_RECIBIDAS'!$I$5:$I$404,'F_RECIBIDAS'!$A$5:$A$404,"PROIM",'F_RECIBIDAS'!$B$5:$B$404,"07") | E38: =SUMIFS('F_RECIBIDAS'!$I$5:$I$404,'F_RECIBIDAS'!$A$5:$A$404,"PROIM",'F_RECIBIDAS'!$B$5:$B$404,"08") | F38: =SUMIFS('F_RECIBIDAS'!$I$5:$I$404,'F_RECIBIDAS'!$A$5:$A$404,"PROIM",'F_RECIBIDAS'!$B$5:$B$404,"09") | G38: =SUM(D38:F38)
B39: Operaciones interiores corrientes — cuota deducible | D39: =SUMIFS('F_RECIBIDAS'!$O$5:$O$404,'F_RECIBIDAS'!$A$5:$A$404,"PROIM",'F_RECIBIDAS'!$B$5:$B$404,"07") | E39: =SUMIFS('F_RECIBIDAS'!$O$5:$O$404,'F_RECIBIDAS'!$A$5:$A$404,"PROIM",'F_RECIBIDAS'!$B$5:$B$404,"08") | F39: =SUMIFS('F_RECIBIDAS'!$O$5:$O$404,'F_RECIBIDAS'!$A$5:$A$404,"PROIM",'F_RECIBIDAS'!$B$5:$B$404,"09") | G39: =SUM(D39:F39)
B40: Bienes de inversión — cuota deducible | G40: =SUM(D40:F40)
B41: ISP soportado — cuota deducible | G41: =SUM(D41:F41)
B42: Cuotas a compensar del periodo anterior | G42: =SUM(D42:F42)
B43: TOTAL DEDUCIBLE | D43: =D39+N(D40)+N(D41)+N(D42) | E43: =E39+N(E40)+N(E41)+N(E42) | F43: =F39+N(F40)+N(F41)+N(F42) | G43: =SUM(D43:F43)
B45: RESULTADO DEL PERIODO | D45: =D35-D43 | E45: =E35-E43 | F45: =F35-F43 | G45: =SUM(D45:F45)
B49: La columna CASILLA se rellena con el número del modelo 303 vigente. Verificar contra el formulario del ejercicio antes de presentar: la numeración cambia entre versiones.

Sheet RETENCIONES
A1: Retenciones — 3T 2026
A2: Si no retienes, respondes tú de lo que debiste retener, aunque el perceptor haya declarado su ingreso.
B4: CONCEPTO | C4: EMPRESA | D4: JULIO | E4: AGOSTO | F4: SEPTIEMBRE | G4: TRIMESTRE | H4: NOTA
B5: MODELO 111 — Rendimientos del trabajo (nóminas) | C5: RP | G5: =SUM(D5:F5) | H5: Sale de la 4751 de la hoja NOMINAS
B6: MODELO 111 — Rendimientos del trabajo (nóminas) | C6: PROIM | G6: =SUM(D6:F6) | H6: Sale de la 4751 de la hoja NOMINAS
B7: MODELO 111 — Profesionales | C7: RP | G7: =SUM(D7:F7) | H7: Facturas donde el pago ≠ total de la factura
B8: MODELO 111 — Profesionales | C8: PROIM | G8: =SUM(D8:F8) | H8: Facturas donde el pago ≠ total de la factura
B9: MODELO 115 — Arrendamiento de local | C9: RP | G9: =SUM(D9:F9) | H9: ¿Se retiene? ¿Hay certificado de exención?
B10: MODELO 115 — Arrendamiento de local | C10: PROIM | G10: =SUM(D10:F10) | H10: ¿Se retiene? ¿Hay certificado de exención?
B12: La cuenta de H.P. acreedora por retenciones tiene que quedar a cero tras el ingreso. Un saldo que se arrastra es una retención practicada y no ingresada.

Sheet CONTROL
A1: Control — no se importa nada a ContaSOL con un cuadre en rojo
A2: Siete comprobaciones. Un fallo aquí invalida todo lo que venga después.
A4: # | B4: COMPROBACIÓN | C4: EMPRESA | D4: ESPERADO | E4: OBTENIDO | F4: DIFERENCIA | G4: ESTADO | H4: SI FALLA
A5: 1 | B5: Diario cuadrado: Σ DEBE = Σ HABER | C5: Las dos | F5: =N(E5)-N(D5) | G5: =IF(AND(N(D5)=0,N(E5)=0),"SIN DATO",IF(ROUND(F5,2)=0,"OK","REVISAR")) | H5: El parseo está mal o hay un asiento descuadrado
A6: 2 | B6: Banco contra contabilidad: saldo extracto = saldo 572 | C6: Las dos | F6: =N(E6)-N(D6) | G6: =IF(AND(N(D6)=0,N(E6)=0),"SIN DATO",IF(ROUND(F6,2)=0,"OK","REVISAR")) | H6: Es el fallo más grave. Se localiza antes de seguir
A7: 3 | B7: Continuidad: saldo final mes N = saldo inicial mes N+1 | C7: Las dos | F7: =N(E7)-N(D7) | G7: =IF(AND(N(D7)=0,N(E7)=0),"SIN DATO",IF(ROUND(F7,2)=0,"OK","REVISAR")) | H7: Falta un extracto o hay movimientos sin contabilizar
A8: 4 | B8: Cuenta de dudas (555) a cero al cierre | C8: Las dos | F8: =N(E8)-N(D8) | G8: =IF(AND(N(D8)=0,N(E8)=0),"SIN DATO",IF(ROUND(F8,2)=0,"OK","REVISAR")) | H8: Cada euro ahí es contabilidad sin terminar
A9: 5 | B9: IVA repercutido de F_EMITIDAS = saldo de la 477 | C9: Las dos | F9: =N(E9)-N(D9) | G9: =IF(AND(N(D9)=0,N(E9)=0),"SIN DATO",IF(ROUND(F9,2)=0,"OK","REVISAR")) | H9: Hay facturas sin contabilizar o mal contabilizadas
A10: 6 | B10: IVA soportado de F_RECIBIDAS = saldo de la 472 | C10: Las dos | F10: =N(E10)-N(D10) | G10: =IF(AND(N(D10)=0,N(E10)=0),"SIN DATO",IF(ROUND(F10,2)=0,"OK","REVISAR")) | H10: Idem, o una deducción aplicada que no procede
A11: 7 | B11: Facturas emitidas correlativas, sin huecos | C11: Las dos | F11: =N(E11)-N(D11) | G11: =IF(AND(N(D11)=0,N(E11)=0),"SIN DATO",IF(ROUND(F11,2)=0,"OK","REVISAR")) | H11: Un hueco en la serie hay que poder explicarlo
A12: 8 | B12: Nóminas: 640+642 = 476+4751+465+460+478 | C12: Las dos | F12: =N(E12)-N(D12) | G12: =IF(AND(N(D12)=0,N(E12)=0),"SIN DATO",IF(ROUND(F12,2)=0,"OK","REVISAR")) | H12: No se genera el asiento hasta que cuadre al céntimo
A13: 9 | B13: Movimientos de banco sin papel | C13: Las dos | F13: =N(E13)-N(D13) | G13: =IF(AND(N(D13)=0,N(E13)=0),"SIN DATO",IF(ROUND(F13,2)=0,"OK","REVISAR")) | H13: Es IVA que hoy no te puedes deducir. Reclamar
B15: Fiabilidad del dato | E15: =IF(COUNTIF(G5:G13,"REVISAR")>0,"BAJA — hay "&COUNTIF(G5:G13,"REVISAR")&" cuadre(s) en rojo",IF(COUNTIF(G5:G13,"SIN DATO")>0,"INCOMPLETA","ALTA"))

Sheet MAESTROS
A1: Maestros
A2: Lo que distingue a cada sociedad. Dar de alta una empresa nueva es añadir sus filas aquí.
A4: EMPRESA | B4: BANCO | C4: CUENTA | D4: SUBCUENTA | E4: TIPO | F4: CUENTA DE DUDAS | G4: NÓMINAS
A5: RP | B5: CaixaBank | C5: 7904 | E5: Corriente | F5: 555000000 | G5: 00094 + 00095 + 00096
A6: RP | B6: CaixaBank | C6: 6108 | E6: Corriente | F6: 555000000
A7: RP | B7: CaixaBank | C7: 9254 | E7: Corriente | F7: 555000000
A8: RP | B8: Bankinter | C8: 4577 | E8: Corriente | F8: 555000000
A9: RP | B9: Bankinter | C9: 3317 | E9: Crédito | F9: 555000000
A10: RP | B10: Sabadell | C10: 2492 | D10: 572000005 | E10: Corriente | F10: 555000000
A11: PROIM | B11: Bankinter | C11: 4584 | D11: 572000001 | E11: Corriente | F11: 555000002 | G11: 00110
A12: PROIM | B12: Sabadell | C12: 0595 | D12: 572000002 | E12: Corriente | F12: 555000002
A13: PROIM | B13: CaixaBank | C13: 5218 | D13: 572000003 | E13: Corriente | F13: 555000002
A14: PROIM | B14: Bankinter | C14: 3303 | D14: 572000004 | E14: Póliza | F14: 555000002
A15: PROIM | B15: CaixaBank | C15: 3940 | D15: 572000005 | E15: Póliza | F15: 555000002
A17: Ojo: 572000005 es Sabadell 2492 en RP y CaixaBank 3940 en PROIM. Son planes contables distintos: nunca identifiques una cuenta por la subcuenta sola.
